vematch/__init__.py
vematch/datasets/__init__.py
vematch/datasets/config_loader.py
vematch/datasets/datasets.yaml
vematch/datasets/downloader.py
vematch/datasets/torch_datasets.py
VeMatch-0.0.2.dist-info/LICENSE
VeMatch-0.0.2.dist-info/METADATA
VeMatch-0.0.2.dist-info/WHEEL
VeMatch-0.0.2.dist-info/top_level.txt
VeMatch-0.0.2.dist-info/RECORD
