Metadata-Version: 2.1
Name: VeMatch
Version: 0.0.2
Summary: A comprehensive toolkit for managing datasets and implementing advanced techniques for similar image identification.
Home-page: https://github.com/gsoaresbaptista/VeMatch
Author: Gabriel Soares Baptista
Author-email: gsoaresbaptista@gmail.com
Classifier: Development Status :: 1 - Planning
Classifier: Intended Audience :: Developers
Classifier: Intended Audience :: Science/Research
Classifier: Topic :: Scientific/Engineering :: Artificial Intelligence
Classifier: Topic :: Scientific/Engineering :: Image Processing
Classifier: Topic :: Software Development :: Libraries :: Python Modules
Classifier: Programming Language :: Python :: 3.10
Classifier: License :: OSI Approved :: MIT License
Classifier: Operating System :: OS Independent
Requires-Python: >=3.12
License-File: LICENSE
Requires-Dist: requests
Requires-Dist: PyYAML
Requires-Dist: tqdm
Requires-Dist: torch
Requires-Dist: torchvision
Requires-Dist: numpy
